xrpa/__debug__.py
xrpa/__init__.py
xrpa/base.py
xrpa/config.py
xrpa/robot.py
xrpa/__pycache__/__init__.cpython-37.pyc
xrpa/__pycache__/base.cpython-37.pyc
xrpa/__pycache__/config.cpython-37.pyc
xrpa/__pycache__/robot.cpython-37.pyc
xrpa-2022.3.14.dist-info/LICENSE
xrpa-2022.3.14.dist-info/METADATA
xrpa-2022.3.14.dist-info/WHEEL
xrpa-2022.3.14.dist-info/entry_points.txt
xrpa-2022.3.14.dist-info/top_level.txt
xrpa-2022.3.14.dist-info/RECORD
