Metadata-Version: 2.1
Name: xrpa
Version: 2022.3.14
Summary: xrpa
Home-page: https://github.com/atpuxiner/xrpa
Author: axiner
Author-email: atpuxiner@163.com
License: MIT
Platform: any
Classifier: License :: OSI Approved :: MIT License
Classifier: Operating System :: OS Independent
Classifier: Programming Language :: Python :: 3
Requires-Python: >=3.6
License-File: LICENSE
